{
  "archive_ts": "2026-03-15T22:55:24",
  "archive_date": "2026-03-15",
  "username": "LT",
  "model": "🟤 豆包 · Seed 2.0 Mini",
  "stock_code": "000002.SZ",
  "stock_name": "万科Ａ",
  "stock_info": {
    "名称": "万科Ａ",
    "行业": "全国地产",
    "地区": "",
    "市场": "",
    "最新价(元)": "4.66",
    "市盈率TTM": "None",
    "市净率PB": "0.3163",
    "市销率PS": "0.1953",
    "总市值(万元)": "5,559,711",
    "换手率(%)": "1.1952",
    "量比": "1.44"
  },
  "price_snapshot": {
    "date": "20260313",
    "open": 4.65,
    "high": 4.73,
    "low": 4.64,
    "close": 4.66,
    "volume": 1161301.32,
    "pct_chg": 0.2151
  },
  "analyses": {
    "expectation": "## 万科Ａ（000002）2026年3月预期差深度分析报告\n**当前日期：2026年03月15日**\n\n---\n\n### 一、核心炒作逻辑拆解\n#### 1. 当前市场叙事\n当前市场对万科A的核心关注逻辑有三点：\n- **超低估值修复**：当前市净率仅0.316，处于历史极低区间，市场预期存在估值修复空间；\n- **业绩拐点预期**：2025年净利润亏损同比收窄39%，市场期待2026年亏损进一步收窄甚至扭亏；\n- **政策催化红利**：2026年全国两会定调地产政策从“止跌回稳”转向“着力稳定”，行业政策边际宽松预期明确。\n\n#### 2. 叙事强度评估\n| 维度 | 判断 |\n|-----|------|\n| 逻辑硬度 | 混合逻辑：硬逻辑（超低PB、业绩同比改善、政策已落地）+ 软逻辑（估值修复持续性、业绩扭亏时间点） |\n| 持续性 | 持续数月的产业趋势：行业政策宽松周期明确，业绩改善为年度级别的边际修复 |\n| 市场认知阶段 | 扩散期：已有3家机构覆盖并给出预测，但目标价（7.68元）与当前股价（4.66元）仍有较大差距，市场尚未形成全面共识 |\n\n---\n\n### 二、市场一致预期锚定\n#### 1. 盈利预期\n截至2026年3月11日，3家券商的一致预测数据：\n- 2025年净利润：**-300.39亿元**，同比增长39.29%（2024年亏损494.78亿元）；\n- 2026年净利润：**-142.79亿元**，亏损幅度同比收窄52.5%；\n- 2027年净利润：预测区间为-223.05亿至-69.08亿元，均值-146.07亿元。\n\n#### 2. 估值预期\n当前万科A市净率0.316，远低于可比公司2026年平均PB 0.6X（东方证券研报数据），市场隐含的核心预期为：万科将持续大额亏损、资产质量进一步恶化。该估值折价具备一定合理性，但存在显著修复空间——若行业政策落地见效，估值修复至0.5-0.6倍PB将对应股价7.37-8.85元。\n\n#### 3. 关键假设与脆弱点\n市场一致预期依赖3个核心假设：\n1.  2026年商品房销售面积同比增速维持5%-10%的修复区间；\n2.  公司减值计提规模维持在合理区间，不会出现超预期大额计提；\n3.  行业政策宽松能够有效带动公司销售去化与现金流改善。\n\n**最脆弱假设**：地产销售修复幅度不及预期，当前居民购房意愿仍偏弱，若三四线城市库存去化缓慢，将直接影响万科结算收入与利润修复进度。\n\n---\n\n### 三、预期差识别\n#### 🟢 正向预期差（可能超预期的变量）\n1.  **政策宽松超预期落地**\n    - 具体因素：2026年政府工作报告明确提出“鼓励收购存量商品房用于保障房”“公积金政策细化优化”，各地已陆续出台针对初婚、多子女家庭的购房贴息、贷款额度提升政策，有望带动刚需与改善性需求释放；\n    - 未充分定价原因：市场仅计价了政策边际宽松的基础预期，但未充分考虑收购存量房、公积金宽松等组合拳对销售的拉动效果；\n    - 验证窗口：2026年4月万科一季报销售数据、2026年1-4月全国商品房销售数据。\n\n2.  **亏损收窄幅度超预期**\n    - 具体因素：若2026年销售增速超过15%，叠加资产处置与减值计提规模低于预期，公司净利润亏损有望收窄至100亿元以内，甚至实现小幅盈利；\n    - 未充分定价原因：当前市场一致预期2026年亏损仍超140亿元，未充分考虑行业政策对公司去化的加速作用；\n    - 验证窗口：2026年4月万科2025年年报、2026年中报结算数据。\n\n3.  **债务风险化解超预期**\n    - 具体因素：公司近1个月多次披露担保进展公告，且互动平台确认无未披露重大信息，若通过盘活存量项目、引入战略合作方实现现金流改善，将无需依赖股东额外资金支持；\n    - 未充分定价原因：当前研报仍提及“关注股东资金支持”，市场对公司自主化解债务风险的能力存疑；\n    - 验证窗口：2026年5月一季报现金流数据、后续资产处置公告。\n\n#### 🔴 负向预期差（可能不及预期的风险）\n1.  **行业销售修复不及预期**\n    - 具体风险：当前全国商品房库存仍处于高位，居民购房意愿修复缓慢，若政策落地效果弱于预期，万科销售增速可能低于5%；\n    - 定价程度：市场已计价了基础修复预期，但未充分考虑极端情况下的销售疲软风险；\n    - 触发条件：2026年4月全国1-3月销售数据低于市场预期。\n\n2.  **大额减值计提超预期**\n    - 具体风险：若2026年部分三四线城市项目去化不及预期，公司可能计提额外减值损失，导致净利润亏损高于市场预期；\n    - 定价程度：市场已计价了常规减值计提，但未充分考虑项目去化缓慢带来的超预期减值；\n    - 触发条件：2026年4月万科2025年年报披露大额减值损失。\n\n#### ⚖️ 预期差净方向判断：偏正\n正向预期差的空间与确定性高于负向风险，政策催化明确，估值修复的核心逻辑未被充分定价。\n\n---\n\n### 四、催化事件日历（2026年3月~6月）\n| 预计时间 | 催化事件 | 影响方向 | 催化强度 | 确定性 |\n|---------|---------|---------|---------|-------|\n| 2026-03-18 | 2026年2月全国商品房销售数据公布 | 正向/中性 | 中 | 高 |\n| 2026-04-28 | 万科A2025年年报披露 | 正向/负向 | 强 | 高 |\n| 2026-04-30 | 万科A2026年一季度销售数据公布 | 正向/负向 | 强 | 高 |\n| 2026-05-20 | 2026年1-4月全国商品房销售数据公布 | 正向/负向 | 中 | 高 |\n| 2026-06-30 | 万科A2026年中期销售数据公布 | 正向/负向 | 中 | 高 |\n| 待定 | 各地出台细化公积金、多子女家庭购房支持政策 | 正向 | 中 | 中 |\n\n---\n\n### 五、情景分析与概率估计\n| 情景 | 核心触发条件 | 目标价区间 | 概率 | 对应策略 |\n|-----|------------|---------|------|---------|\n| 🟢 乐观 | 1. 2026年1-3月全国商品房销售增速＞15%；2. 万科2025年年报减值计提＜50亿元；3. 各地出台超预期购房补贴政策 | 7.00-9.00元 | 30% | 加仓/增持 |\n| 🟡 中性 | 维持一致预期：2026年净利润亏损收窄至140亿元左右，行业销售增速5%-10% | 5.00-6.50元 | 50% | 持有 |\n| 🔴 悲观 | 1. 全国商品房销售增速＜5%；2. 万科2025年年报减值计提＞80亿元；3. 行业政策落地不及预期 | 3.50-4.50元 | 20% | 减仓/观望 |\n*三种情景概率合计100%*\n\n---\n\n### 六、预期差裁决\n**综合评分：7/10**\n评分依据：存在明确的正向预期差，政策催化时间窗口清晰，但行业销售修复的不确定性仍存在。\n\n**筛选结论：✅存在显著预期差**\n\n**核心理由：**\n1.  预期差本质：市场低估了2026年地产组合政策的落地效果，以及万科超低估值的修复空间，同时对公司债务风险化解能力过于悲观；\n2.  催化剂兑现时间：核心催化节点为2026年4月的年报与一季度销售数据，政策细化落地将提前催化行情；\n3.  当前定价状态：4.66元的股价仅对应0.316倍PB，尚未充分反映行业政策宽松与业绩改善的预期。",
    "trend": "### 一、K线形态识别\n当前万科A处于**下跌后的缩量震荡企稳形态**：2月下旬冲高至5.00元后放量大跌，最低探至4.59元（60日区间最低价），此后进入窄幅震荡，近5日在4.62-4.73元区间僵持，成交量逐步萎缩，抛压大幅缓解。\n- **关键支撑位**：4.59元（60日最低价、前期震荡低点）、4.60-4.65元（近几日密集成交低点）\n- **关键压力位**：4.79元（MA20/布林带中轨）、4.90-5.00元（前期反弹高点区间）、4.83元（60日均线）\n\n---\n### 二、均线系统解读\n当前属于**标准空头排列**：\nMA5=4.66元、MA20=4.79元、MA60=4.83元，短期均线位于中长期均线下方，且MA5尚未上穿MA20，无金叉信号；MACD的DIF=-0.06、DEA=-0.05，DIF仍在DEA下方，空头信号持续；股价运行在布林带中轨下方，处于弱势区间，整体均线趋势未出现反转。\n\n---\n### 三、量价关系分析\n1.  **量能特征**：2月26日大跌时放出阶段天量（278万手），集中释放抛压；此后成交量持续萎缩，近5日维持在60-120万手区间，3月15日成交量116万手、量比1.44，相比前期略有放大，说明多空进入僵持阶段，抛压已大幅缓解。\n2.  **量价配合**：放量下跌后缩量震荡，属于弱势企稳信号，未出现放量反弹，说明多头力量尚未完全复苏，但空头也无继续砸盘动能。\n3.  **主力信号**：3月5日主力资金净流入4743.58万元，当日股价上涨1.52%，显示有资金在低位承接；3月15日成交额放大至5.44亿元，配合小幅上涨，主力仍在缓慢吸筹。\n\n---\n### 四、资金动向综合研判\n1.  **净流入/流出趋势**：\n    - 短期主力资金小幅净流入，3月5日、3月15日均有资金低位承接，整体未出现大规模出逃；\n    - 融资融券：3月12日融资余额30.88亿元，融资净买入额为-281.6万元，杠杆资金整体偏谨慎，但未大规模撤离；\n    - 北向资金：根据2025年三季报数据，香港中央结算有限公司加仓1708.68万股，仍为前十大流通股东，外资长期持仓态度偏稳健。\n2.  **龙虎榜与筹码**：近30日无龙虎榜记录，无游资炒作；当前股价低于MA20/MA60，前期4.8-5.0元为套牢筹码密集区，近期4.6-4.7元为低位新筹码集中区。\n3.  **主力行为判断**：结合缩量震荡+低位吸筹的特征，主力并非出货，而是在**缓慢低位建仓**，但受整体空头趋势限制，建仓节奏较为平缓。\n\n---\n### 五、中短线趋势研判\n#### 📌 短线展望（1-2周）：\n- 趋势：**震荡偏多**，低位企稳后有望冲击中轨压力位\n- 买入参考：**4.60-4.65元**（低位震荡区间下沿）\n- 止损：**4.59元**（跌破则确认继续下探）\n- 目标：首先看到**4.79元（MA20/布林中轨）**，突破后看向4.90-5.00元区间\n\n#### 📌 中线展望（1-3个月）：\n- 趋势方向：**震荡反弹**，理由是股价已接近60日最低价，抛压释放完毕，叠加主力低位吸筹，若地产政策边际改善，有望推动估值修复；但公司年报预亏820亿元，基本面仍有压力，难有大级别行情。\n- 目标区间：**4.8元 ~ 5.2元**（60日最高价附近）\n- 支撑：**4.59元（前期低点）、4.65元（近几日震荡低点）**\n\n---\n### 六、技术面裁决\n**综合评分：4 / 10**（10=极强技术买入信号，1=强烈技术卖出信号）\n**筛选结论：** ⚠️技术面中性观望\n**核心理由：**\n1.  均线仍处于空头排列，MACD空头信号未解除，整体趋势偏弱；\n2.  短线有企稳迹象，量能缩量后温和放大，主力有低位吸筹动作，但缺乏强势反弹的量能配合；\n3.  公司基本面仍有业绩亏损压力，仅适合短线轻仓低吸，中线需等待均线修复与政策利好确认。",
    "fundamentals": "## 一、财务健康体检\n\n| 维度 | 评估内容 | 近期表现/趋势 | 评级（⭐1-5）|\n|-----|---------|------------|------------|\n| 成长性 | 营收/净利润CAGR | 营收同比下滑26.61%，净利润连续4个季度大额亏损，2025Q3同比下滑56.14%，成长性完全丧失 | 1⭐ |\n| 盈利质量 | 净利率、现金含量、扣非 | 净利率-17.5%，毛利率仅9.58%，经营性现金流为负，扣非净利润同步大额亏损，三费占营收比高达8.92%，盈利质量极差 | 1⭐ |\n| 偿债安全 | 资负率、流动/速动比 | 资产负债率73.51%，速动比率仅0.6，货币资金/流动负债仅14.02%，公开市场融资渠道不畅，短期偿债压力极大 | 1⭐ |\n| 资本效率 | ROE近3年、ROIC | ROE持续为负，2024年ROIC为-5.9%，2025年持续亏损，资本效率极差 | 1⭐ |\n| 现金流 | 经营现金流 vs 净利润 | 2025Q1经营性现金流净额-57.93亿，每股经营性现金流-0.49元，与净利润大额亏损完全匹配，现金流极度紧张 | 1⭐ |\n\n**财务健康评分：1 / 10**\n\n---\n\n## 二、盈利质量深析\n- 利润真实性：公司2025年前三季度归母净利润亏损280.16亿元，当期新增计提大额存货跌价准备，联合营项目大幅亏损、投资收益暴跌4129.92%，同时存在资产减值损失、信用减值损失等多项非经营性亏损，主业盈利能力彻底失效。\n- 财务水分风险：公司存货/营收占比高达123.28%，存在较大的存货跌价计提压力；货币资金对流动负债的覆盖能力极弱，同时存在其他应收款坏账风险，财务报表真实性存疑，存在通过大额计提进行财务洗澡的嫌疑。\n\n---\n\n## 三、核心竞争力评估\n- 护城河类型及宽度：万科曾经的品牌、土地储备、融资能力、万物云物业护城河已大幅收窄：销售业绩持续下滑，新项目储备不足，公开市场融资渠道受阻，仅大股东深铁集团的支持尚能维持基本流动性，但主业盈利能力已经无法支撑原有护城河宽度。\n- 行业地位与竞争格局：万科仍处于地产行业第一梯队，但在国企开发商主导的行业格局下，民企融资、拿地优势尽失，市场份额持续下滑，行业竞争力被显著削弱。\n\n---\n\n## 四、估值分析\n| 指标 | 当前值 | 历史分位 | 行业均值 | 判断 |\n|-----|-------|--------|---------|-----|\n| PE(TTM) | None | - | 约8-12倍 | 净利润为负，无参考意义 |\n| PB | 0.3163 | 历史极低分位 | 约0.5-0.8倍 | 显著低于行业平均，但破净源于持续亏损 |\n| PS | 0.1953 | 历史极低分位 | 约0.2-0.4倍 | 显著低于行业平均 |\n| 股息率 | 0% | - | 约2%-3% | 2024年及2025年连续亏损，无分红能力 |\n\n**估值结论：** ⚠️谨慎低估\n静态估值指标显著偏低，但公司持续大额亏损将持续侵蚀净资产，估值修复空间有限，存在价值陷阱风险。\n\n---\n\n## 五、风险预警雷达 🚨\n1.  **财务风险**：连续多季度大额亏损，经营性现金流为负，短期偿债压力极大，存货跌价、联合营项目亏损等风险持续暴露。\n2.  **股东风险**：公开市场债券融资渠道不畅，面临较大的信用债集中到期压力，虽有大股东支持，但流动性风险仍高。\n3.  **经营风险**：销售业绩持续下滑，新项目储备不足，行业竞争加剧，主业盈利能力无法改善。\n4.  **估值风险**：虽估值指标偏低，但持续亏损导致净资产不断缩水，估值修复难度极大。\n\n---\n\n## 六、基本面裁决\n**综合评分：1 / 10**\n**筛选结论：** ❌不通过\n**核心理由：** 万科A连续多个季度大额亏损，盈利质量极差，经营性现金流紧张，短期偿债压力极大，核心竞争力大幅受损，基本面已经严重恶化，属于典型的垃圾公司范畴，不符合投资筛选标准。"
  },
  "analyses_validated": [
    "expectation",
    "trend",
    "fundamentals"
  ],
  "moe_results": null
}